multyverse/__init__.py
multyverse-0.0.0.dist-info/METADATA
multyverse-0.0.0.dist-info/WHEEL
multyverse-0.0.0.dist-info/RECORD
